horizon
openstack_auth
openstack_dashboard
