Metadata-Version: 2.1
Name: horizon
Version: 25.5.0
Summary: OpenStack Dashboard
Home-page: https://docs.openstack.org/horizon/latest/
Author: OpenStack
Author-email: openstack-discuss@lists.openstack.org
Classifier: Development Status :: 5 - Production/Stable
Classifier: Environment :: OpenStack
Classifier: Framework :: Django
Classifier: Intended Audience :: Developers
Classifier: Intended Audience :: Information Technology
Classifier: Intended Audience :: System Administrators
Classifier: License :: OSI Approved :: Apache Software License
Classifier: Operating System :: OS Independent
Classifier: Operating System :: POSIX :: Linux
Classifier: Programming Language :: Python
Classifier: Programming Language :: Python :: 3 :: Only
Classifier: Programming Language :: Python :: 3
Classifier: Programming Language :: Python :: 3.9
Classifier: Programming Language :: Python :: 3.10
Classifier: Programming Language :: Python :: 3.11
Classifier: Topic :: Internet :: WWW/HTTP
Requires-Python: >=3.9
License-File: LICENSE
License-File: AUTHORS
Requires-Dist: pbr >=5.5.0
Requires-Dist: Babel >=2.6.0
Requires-Dist: Django <4.3,>=4.2
Requires-Dist: django-compressor >=4.4
Requires-Dist: django-debreach >=1.4.2
Requires-Dist: futurist >=1.2.0
Requires-Dist: iso8601 >=0.1.11
Requires-Dist: keystoneauth1 >=4.3.1
Requires-Dist: netaddr >=0.7.18
Requires-Dist: oslo.concurrency >=4.5.0
Requires-Dist: oslo.config >=8.8.0
Requires-Dist: oslo.i18n >=5.1.0
Requires-Dist: oslo.policy >=3.11.0
Requires-Dist: oslo.serialization >=4.3.0
Requires-Dist: oslo.upgradecheck >=1.5.0
Requires-Dist: oslo.utils >=7.0.0
Requires-Dist: osprofiler >=3.4.2
Requires-Dist: libsass >=0.23.0
Requires-Dist: Pillow >=9.1.0
Requires-Dist: python-cinderclient >=8.0.0
Requires-Dist: python-glanceclient >=2.8.0
Requires-Dist: python-keystoneclient >=3.22.0
Requires-Dist: python-neutronclient >=8.1.0
Requires-Dist: python-novaclient >=9.1.0
Requires-Dist: python-swiftclient >=3.2.0
Requires-Dist: PyYAML >=6.0
Requires-Dist: qrcode >=8.2
Requires-Dist: requests >=2.25.1
Requires-Dist: semantic-version >=2.3.1
Requires-Dist: tzdata >=2022.4
Requires-Dist: XStatic >=1.0.3
Requires-Dist: XStatic-Angular >=1.8.2.2
Requires-Dist: XStatic-Angular-Bootstrap >=2.2.0.0
Requires-Dist: XStatic-Angular-FileUpload >=12.0.4.0
Requires-Dist: XStatic-Angular-Gettext >=2.3.8.0
Requires-Dist: XStatic-Angular-lrdragndrop >=1.0.2.2
Requires-Dist: XStatic-Angular-Schema-Form >=0.8.13.0
Requires-Dist: XStatic-Bootstrap-Datepicker >=1.3.1.0
Requires-Dist: XStatic-Bootstrap-SCSS >=3.3.7.1
Requires-Dist: XStatic-bootswatch >=3.3.7.0
Requires-Dist: XStatic-D3 >=3.5.17.0
Requires-Dist: XStatic-Hogan >=2.0.0.2
Requires-Dist: XStatic-Font-Awesome >=4.7.0.0
Requires-Dist: XStatic-Jasmine >=2.4.1.1
Requires-Dist: XStatic-jQuery >=3.5.1.1
Requires-Dist: XStatic-JQuery-Migrate >=3
Requires-Dist: XStatic-JQuery.quicksearch >=2.0.3.2
Requires-Dist: XStatic-JQuery.TableSorter >=2.14.5.1
Requires-Dist: XStatic-jquery-ui >=1.13.0.1
Requires-Dist: XStatic-JSEncrypt >=2.3.1.1
Requires-Dist: XStatic-mdi >=1.6.50.2
Requires-Dist: XStatic-objectpath >=1.2.1.0
Requires-Dist: XStatic-Rickshaw >=1.5.0.0
Requires-Dist: XStatic-roboto-fontface >=0.5.0.0
Requires-Dist: XStatic-smart-table >=1.4.13.2
Requires-Dist: XStatic-Spin >=1.2.5.2
Requires-Dist: XStatic-term.js >=0.0.7.0
Requires-Dist: XStatic-tv4 >=1.2.7.0
Requires-Dist: enmerkar >=0.7.1
